pygifconvt_lsw/__init__.py
pygifconvt_lsw/converter.py
pygifconvt_lsw-1.0.2.dist-info/LICENSE
pygifconvt_lsw-1.0.2.dist-info/METADATA
pygifconvt_lsw-1.0.2.dist-info/WHEEL
pygifconvt_lsw-1.0.2.dist-info/top_level.txt
pygifconvt_lsw-1.0.2.dist-info/RECORD
