Metadata-Version: 2.1
Name: pygifconvt-lsw
Version: 1.0.2
Summary: lsw's Test Package
Home-page: UNKNOWN
Author: peterlah
Author-email: peterlah@naver.com
License: UNKNOWN
Keywords: GIFCONVERTER,gifconverter
Platform: UNKNOWN
Classifier: Programming Language :: Python :: 3
Classifier: License :: OSI Approved :: MIT License
Classifier: Operating System :: OS Independent
Requires-Python: >=3
License-File: LICENSE
Requires-Dist: pillow
